Metadata-Version: 2.1
Name: pytest-beeprint
Version: 0.1.1
Summary: use icdiff for better error messages in pytest assertions
Home-page: https://github.com/hjwp/pytest-beeprint
Author: Rodrigo Ferreira de Souza
Author-email: rodfersou@gmail.com
Maintainer: Rodrigo Ferreira de Souza
Maintainer-email: rodfersou@gmail.com
License: Unlicense
Classifier: Development Status :: 4 - Beta
Classifier: Framework :: Pytest
Classifier: Intended Audience :: Developers
Classifier: Topic :: Software Development :: Testing
Classifier: Programming Language :: Python
Classifier: Programming Language :: Python :: 3.7
Classifier: Programming Language :: Python :: 3.8
Classifier: Programming Language :: Python :: 3.9
Classifier: Programming Language :: Python :: 3.10
Classifier: Programming Language :: Python :: 3.11
Classifier: Operating System :: OS Independent
Classifier: License :: Public Domain
Requires-Python: >=3.7
License-File: LICENSE
